<?xml version='1.0'?>
<coherence
	xmlns:xsi="http://www.w3.org/2001/XMLSchema-instance"
	xmlns="http://xmlns.oracle.com/coherence/coherence-operational-config"
	xsi:schemaLocation="http://xmlns.oracle.com/coherence/coherence-operational-config
   coherence-operational-config.xsd">
	<cluster-config>
		<member-identity>
			<role-name>storage</role-name>
		</member-identity>
		
		<shutdown-listener>
			<enabled system-property="coherence.shutdownhook">graceful</enabled>
		</shutdown-listener>
	</cluster-config>

	<configurable-cache-factory-config>
		<init-params>
			<init-param>
				<param-type>java.lang.String</param-type>
				<param-value system-property="tangosol.coherence.cacheconfig">
					coherence-cache-config.xml
				</param-value>
			</init-param>
		</init-params>
	</configurable-cache-factory-config>
	
</coherence>